flatdict2.py
flatdict2-4.0.4.dist-info/LICENSE
flatdict2-4.0.4.dist-info/METADATA
flatdict2-4.0.4.dist-info/WHEEL
flatdict2-4.0.4.dist-info/top_level.txt
flatdict2-4.0.4.dist-info/zip-safe
flatdict2-4.0.4.dist-info/RECORD
